grokcli/__init__.py
grokcli/__version__.py
grokcli/api.py
grokcli/datadogcli.py
grokcli/exceptions.py
grokcli/vmware.py
grokcli/commands/DELETE.py
grokcli/commands/GET.py
grokcli/commands/POST.py
grokcli/commands/__init__.py
grokcli/commands/autostacks.py
grokcli/commands/cloudwatch.py
grokcli/commands/credentials.py
grokcli/commands/custom.py
grokcli/commands/export.py
grokcli/commands/import.py
grokcli/commands/instances.py
grokcli/commands/metrics.py
grokcli-2.7.1.dist-info/DESCRIPTION.rst
grokcli-2.7.1.dist-info/METADATA
grokcli-2.7.1.dist-info/RECORD
grokcli-2.7.1.dist-info/WHEEL
grokcli-2.7.1.dist-info/entry_points.txt
grokcli-2.7.1.dist-info/metadata.json
grokcli-2.7.1.dist-info/top_level.txt
