Metadata-Version: 2.0
Name: grokcli
Version: 2.7.1
Summary: Grok Command Line Interface
Home-page: https://github.com/grokstream/grok-cli
Author: Avik Partners, LLC
Author-email: support@grokstream.com
License: UNKNOWN
Keywords: grok,grokstream,anomaly detection,monitoring
Platform: UNKNOWN
Classifier: Development Status :: 5 - Production/Stable
Classifier: Environment :: Console
Classifier: Intended Audience :: Developers
Classifier: Intended Audience :: Information Technology
Classifier: License :: OSI Approved :: Apache Software License
Classifier: Programming Language :: Python :: 2
Classifier: Topic :: Utilities
Requires-Dist: certifi
Requires-Dist: prettytable
Requires-Dist: pysphere
Requires-Dist: pyyaml
Requires-Dist: requests
Provides-Extra: docs
Requires-Dist: sphinx; extra == 'docs'
Provides-Extra: samples
Requires-Dist: datadog; extra == 'samples'
